lightcurve/__init__.py
lightcurve/buffer.py
lightcurve/client.py
lightcurve/context.py
lightcurve/logger.py
lightcurve/monitor.py
lightcurve/schemas.py
lightcurve/tracer.py
lightcurve/transport.py
lightcurve/integrations/__init__.py
lightcurve/integrations/anthropic.py
lightcurve/integrations/gemini.py
lightcurve/integrations/langchain.py
lightcurve/integrations/litellm.py
lightcurve/integrations/openai.py
use_lightcurve-0.2.4.dist-info/licenses/LICENSE
use_lightcurve-0.2.4.dist-info/METADATA
use_lightcurve-0.2.4.dist-info/WHEEL
use_lightcurve-0.2.4.dist-info/top_level.txt
use_lightcurve-0.2.4.dist-info/RECORD
